{
    "version": "5.0.beta.3.0",
    "collection": [
        {
            "class_name": "DataTable",
            "id": 4,
            "name": "default_data_table",
            "description": "",
            "accessibility": 2,
            "protected": "0",
            "archived": "0",
            "columns": [
                {
                    "name": "id",
                    "type": "bigint",
                    "nullable": false
                },
                {
                    "name": "name",
                    "type": "string",
                    "nullable": false
                },
                {
                    "name": "value",
                    "type": "text",
                    "nullable": false
                },
                {
                    "name": "session_id",
                    "type": "string",
                    "nullable": false
                },
                {
                    "name": "data_set_id",
                    "type": "string",
                    "nullable": false
                }
            ],
            "updatedOn": "2017-04-10 19:32:52",
            "updatedByName": "",
            "owner": 1,
            "groups": "",
            "starterContent": true,
            "rev": 4,
            "hash": "a06baaf69b32ee53e3d6de9a6e739403812d8815",
            "data": []
        }
    ]
}