[
    {
        "class_name": "DataTable",
        "id": 23,
        "name": "default_data_table",
        "description": "",
        "accessibility": 0,
        "protected": "0",
        "archived": "0",
        "columns": [
            {
                "name": "id",
                "type": "bigint",
                "nullable": false
            },
            {
                "name": "session_id",
                "type": "bigint",
                "nullable": false
            },
            {
                "name": "name",
                "type": "string",
                "nullable": false
            },
            {
                "name": "value",
                "type": "text",
                "nullable": false
            }
        ],
        "updatedOn": "2016-04-07 01:04:01",
        "updatedByName": "",
        "globalId": "1459984402-23-2233",
        "owner": 1,
        "groups": "",
        "revision": 25,
        "checksum": "5ea1851a52afd98a71f4536e83fb38df",
        "starterContent": true,
        "data": [

        ]
    }
]